setup.py
GandB_distributions_chauhan.shi.egg-info/PKG-INFO
GandB_distributions_chauhan.shi.egg-info/SOURCES.txt
GandB_distributions_chauhan.shi.egg-info/dependency_links.txt
GandB_distributions_chauhan.shi.egg-info/top_level.txt
distributions/Binomialdistribution.py
distributions/Gaussiandistribution.py
distributions/Generaldistribution.py
distributions/__init__.py