Metadata-Version: 2.1
Name: GandB-distributions-chauhan.shi
Version: 0.0.1
Summary: Guassian and Binomial distribution package
Home-page: https://github.com/Chauhanshi/GaussianBinomial-distribution-python-package
Author: Shivam Chauhan
Author-email: shivam.chauhan21@gmail.com
License: UNKNOWN
Platform: UNKNOWN
Classifier: Programming Language :: Python :: 3
Classifier: License :: OSI Approved :: MIT License
Classifier: Operating System :: OS Independent
Requires-Python: >=3.6
